pyvantagepro/__init__.py
pyvantagepro/__main__.py
pyvantagepro/compat.py
pyvantagepro/device.py
pyvantagepro/link.py
pyvantagepro/logger.py
pyvantagepro/parser.py
pyvantagepro/utils.py
pyvantagepro/tests/__init__.py
pyvantagepro/tests/test_parser.py
pyvantagepro/tests/test_utils.py
PyVantagePro_MarcoGos-0.3.27.dist-info/AUTHORS.rst
PyVantagePro_MarcoGos-0.3.27.dist-info/LICENSE
PyVantagePro_MarcoGos-0.3.27.dist-info/METADATA
PyVantagePro_MarcoGos-0.3.27.dist-info/WHEEL
PyVantagePro_MarcoGos-0.3.27.dist-info/top_level.txt
PyVantagePro_MarcoGos-0.3.27.dist-info/RECORD
