Metadata-Version: 2.2
Name: PyVantagePro_MarcoGos
Version: 0.3.27
Summary: Communication tools for the Davis VantagePro2 devices
Author-email: Salem Harrache <salem.harrache@gmail.com>, Marco Gosselink <pypi@famgosselink.nl>
License:                     GNU GENERAL PUBLIC LICENSE
Project-URL: Homepage, https://github.com/MarcoGos/PyVantagePro
Project-URL: Issues, https://github.com/MarcoGos/PyVantagePro/issues
Classifier: Development Status :: 4 - Beta
Classifier: Intended Audience :: Science/Research
Classifier: Intended Audience :: Developers
Classifier: License :: OSI Approved :: GNU General Public License v3 (GPLv3)
Classifier: Programming Language :: Python :: 2
Classifier: Programming Language :: Python :: 2.6
Classifier: Programming Language :: Python :: 2.7
Classifier: Programming Language :: Python :: 3
Classifier: Programming Language :: Python :: 3.2
Classifier: Topic :: Internet
Classifier: Topic :: Utilities
Classifier: Topic :: Software Development :: Libraries :: Python Modules
Requires-Python: >=3.8
License-File: LICENSE
License-File: AUTHORS.rst
Requires-Dist: progressbar-latest
